rfsed/ExtractEq.py
rfsed/ExtractEqMultiproc.py
rfsed/ReverbFilter.py
rfsed/SynthAnalysis.py
rfsed/WaveformFitting.py
rfsed/WaveformFittingMultiproc.py
rfsed/__init__.py
rfsed/__version__.py
rfsed/hkSeqYeck.py
rfsed/hkYu.py
rfsed/hkZhu.py
rfsed/synrf.py
rfsed/util.py
rfsed/data/__init__.py
rfsed/data/Earthquake_Catalog/__init__.py
rfsed/data/Earthquake_Catalog/eq_events.quakeml
rfsed/data/Raw_Data/OPLO.2020.02.13.mseed
rfsed/data/Raw_Data/OPLO.2020.05.15.mseed
rfsed/data/rfstreams_Moho/__init__.py
rfsed/data/rfstreams_Moho/rfstreams.h5
rfsed/data/rfstreams_Sed/__init__.py
rfsed/data/rfstreams_Sed/rfstreams.h5
rfsed/examples/__init__.py
rfsed/examples/Calculated_Receiver_Functions/00_rf_data.h5
rfsed/examples/Calculated_Receiver_Functions/__init__.py
rfsed/examples/IRIS_Downloaded_Waveform/00_eq_data.h5
rfsed/examples/IRIS_Downloaded_Waveform/00_eq_events.xml
rfsed/examples/IRIS_Downloaded_Waveform/00_eq_stations.xml
rfsed/examples/IRIS_Downloaded_Waveform/__init__.py
rfsed/examples/catalog/__init__.py
rfsed/examples/catalog/eq_events.quakeml
rfsed/examples/earthquake_data/__init__.py
rfsed/examples/earthquake_data/Extracted_Eq_Data/__init__.py
rfsed/examples/earthquake_data/Extracted_Eq_Data/eq_data.h5
rfsed/examples/earthquake_data/Extracted_Eq_Data_Multiproc/__init__.py
rfsed/examples/earthquake_data/Extracted_Eq_Data_Multiproc/eq_data.h5
rfsed/examples/notebooks/Example10_Synthethic_Receiver_Function_Analysis.ipynb
rfsed/examples/notebooks/Example11_Waveform_Fitting_of_Receiver_Functions.ipynb
rfsed/examples/notebooks/Example12_Waveform_Fitting(Multiprocessing)_of_Receiver_Functions.ipynb.ipynb
rfsed/examples/notebooks/Example1_Download_Waveform_Data_from_IRIS.ipynb
rfsed/examples/notebooks/Example2_Calculate_Receiver_Functions.ipynb
rfsed/examples/notebooks/Example3_example_Get_Catalog.ipynb
rfsed/examples/notebooks/Example4_Extract_Earthquake_Waveform_from_Local_Data.ipynb
rfsed-1.0.0.dist-info/LICENSE
rfsed-1.0.0.dist-info/METADATA
rfsed-1.0.0.dist-info/WHEEL
rfsed-1.0.0.dist-info/top_level.txt
rfsed-1.0.0.dist-info/RECORD
