Metadata-Version: 2.1
Name: rfsed
Version: 1.0.0
Summary: Package for receiver functions analysis and dealing with sediment effects in receiver functions
Home-page: https://github.com/akinremisa/rfsed
Author: Stephen Akinremi
Author-email: s.akinremi@utwente.nl
Keywords: Seismology,Receiver Function,Sediment effect in receiver functions,Crustal modelling,Moho,Earth Sciences
Classifier: Programming Language :: Python :: 3
Classifier: License :: OSI Approved :: BSD License
Classifier: Operating System :: OS Independent
Classifier: Topic :: Scientific/Engineering :: Physics
Requires-Python: <3.11,>=3.6
License-File: LICENSE
Requires-Dist: obspy >=1.0.3
Requires-Dist: rf >=1.0.3
Requires-Dist: numpy <=1.24.0
Requires-Dist: obspyh5
Requires-Dist: matplotlib
Requires-Dist: tqdm
Requires-Dist: pytest >=7.4.4
Requires-Dist: scikit-learn
Requires-Dist: seaborn
Requires-Dist: colorama
Requires-Dist: OWSLib
Requires-Dist: plotly
Requires-Dist: psutil
Requires-Dist: pyyaml
Requires-Dist: pytz >=2020.1
Requires-Dist: importlib-metadata
Provides-Extra: docs
Requires-Dist: sphinx <6.0 ; extra == 'docs'
Requires-Dist: pydata-sphinx-theme ; extra == 'docs'
Requires-Dist: sphinx-copybutton ; extra == 'docs'
Requires-Dist: sphinx-gallery ; extra == 'docs'
Requires-Dist: jinja2 <3.1 ; extra == 'docs'
Provides-Extra: tests
Requires-Dist: pytest ; extra == 'tests'
Requires-Dist: py ; extra == 'tests'
